{
    "name": "Ika Carter",
    "age": 18,
    "known traits": [
        "brave",
        "outgoing"
    ],
    "all traits": [
        "brave",
        "outgoing",
        "egocentric",
        "slow",
        "lazy"
    ],
    "guardian": {
        "name": "Paul",
        "surname": "Carter",
        "age": 72,
        "sex": "m",
        "relation": "uncle",
        "location": [
            "Yankalilla",
            "South Australia",
            "Australia",
            "town"
        ],
        "income_class": 3,
        "lifestyle": 3,
        "married": false,
        "other_children": false,
        "nurturing": true,
        "provide_college": true,
        "provide_women_college": false,
        "provide_boarding_school": false,
        "allowance": "big allowance",
        "capacity": 0,
        "ward": [
            "Ika"
        ]
    },
    "location": [
        "Yankalilla",
        "South Australia",
        "Australia",
        "town"
    ],
    "lifestyle": 3,
    "income class": 3,
    "boarding school": false,
    "country affinities": {
        "Netherlands": 0,
        "Indonesia": 2,
        "Australia": 1
    },
    "sexuality": "gay",
    "relationships": {
        "Juana": 100,
        "Jules": 73,
        "Robin": 68,
        "Paul Carter": 82
    },
    "person tags": {
        "love_interest": null,
        "old_flame": null,
        "partner": null,
        "spouse": null,
        "affairpartner": null,
        "dead_partner": null,
        "dead_child": null,
        "children": [],
        "extra_marital_children": [],
        "ex_spouses": [],
        "ex_partners": [],
        "boss": null,
        "colleague": null,
        "guardian": "Paul Carter",
        "friend": null,
        "bestfriend": null,
        "deadfriend": null,
        "bfriend": null,
        "childhoodfriend": null,
        "familyfriend": null,
        "pet": null,
        "enemy": null
    },
    "trauma": 35,
    "happinness": 80,
    "aspirations": {
        "lifestyle": 3,
        "income": 3,
        "children": true,
        "location": "Indonesia",
        "college": false,
        "ambitious": false,
        "independent": false
    }
}