{
    "name": "Ika Nicolaas",
    "age": 18,
    "known traits": [
        "brave",
        "outgoing"
    ],
    "all traits": [
        "brave",
        "outgoing",
        "empathetic",
        "straight-laced",
        "daydreamer"
    ],
    "guardian": {
        "name": "Diane",
        "surname": "Schwarze",
        "age": 55,
        "relation": "sister",
        "location": [
            "Geelong",
            "Victoria",
            "Australia",
            "town"
        ],
        "income_class": "medium",
        "lifestyle": "rich",
        "married": true,
        "other_children": false,
        "nurturing": false,
        "provide_college": true,
        "provide_women_college": true,
        "provide_boarding_school": true,
        "allowance": "medium allowance",
        "capacity": 1,
        "ward": [
            "Ika"
        ]
    },
    "location": [
        "Geelong",
        "Victoria",
        "Australia",
        "town"
    ],
    "lifestyle": "rich",
    "income class": "medium",
    "boarding school": true,
    "country affinities": {
        "Netherlands": 1,
        "Indonesia": 0,
        "Australia": 1
    },
    "sexuality": "gay",
    "relationships": {
        "Juana": 93,
        "Jules": 47,
        "Robin": 64,
        "Diane Schwarze": 5
    },
    "person tags": {
        "guardian": "Diane Schwarze"
    },
    "trauma": 8,
    "happinness": 80,
    "aspirations": {
        "lifestyle": "lavish",
        "income": "very high",
        "children": false,
        "location": "Netherlands",
        "college": false
    }
}